{
  "expo": {
    "name": "prototype",
    "slug": "prototype",

    "android":{
      "packagge": "com.PDXCapstone2020Spring.safespace",
      "versionCode": 1
    },
    "platforms": [
      "ios",
      "android",
      "web"
    ],
    "version": "1.0.0",
    "orientation": "portrait",
    "icon": "./assets/icon.png",
    "splash": {
      "image": "./assets/splash.png",
      "resizeMode": "contain",
      "backgroundColor": "#ffffff"
    },
    "updates": {
      "fallbackToCacheTimeout": 0
    },
    "assetBundlePatterns": [
      "**/*"
    ],
    "ios": {
      "supportsTablet": true
    },
    "description": "",
    "android": {
      "package": "com.yourcompany.yourappname",
      "versionCode": 1
    }
  }
}
